montty/__init__.py
montty/montty_checker.py
montty/montty_deployer.py
montty/montty_manager.py
montty/montty_meta.py
montty/montty_monitor.py
montty/app/__init__.py
montty/app/status.py
montty/app/check/__init__.py
montty/app/check/bash_check.py
montty/app/check/check.py
montty/app/check/check_app.py
montty/app/check/check_body.py
montty/app/check/check_header.py
montty/app/check/check_level.py
montty/app/check/collect_all_check.py
montty/app/check/collect_base_check.py
montty/app/check/collect_depend_check.py
montty/app/check/python_check.py
montty/app/check/root_check.py
montty/app/check/file/__init__.py
montty/app/check/file/check_file_parser.py
montty/app/check/file/dynamic_import.py
montty/app/manager/__init__.py
montty/app/manager/manager_app.py
montty/app/monitor/__init__.py
montty/app/monitor/monitor_app.py
montty/io/__init__.py
montty/io/screen.py
montty/io/dir/__init__.py
montty/io/dir/bash_scripts_dir.py
montty/io/dir/checks_dir.py
montty/io/dir/data_files_dir.py
montty/io/dir/install_dir.py
montty/io/dir/python_libs_dir.py
montty/io/dir/reports_dir.py
montty/io/file/__init__.py
montty/io/file/check_tags_file.py
montty/io/file/file_name.py
montty/io/file/file_reader.py
montty/io/file/file_util.py
montty/io/file/file_writer.py
montty/io/file/msg_name.py
montty/montty_deploy/__init__.py
montty/montty_deploy/deploy_dir.py
montty/montty_deploy/run.sh
montty/montty_deploy/spy.sh
montty/montty_deploy/CHECKS/__init__.py
montty/montty_deploy/CHECKS/_chk_005_cld_bash_sudo_ufw.py
montty/montty_deploy/CHECKS/_chk_006_cld_bash_data_sudo_lsof.py
montty/montty_deploy/CHECKS/checks.csv
montty/montty_deploy/CHECKS/chk_001_bash_listening_ports_with_ss.py
montty/montty_deploy/CHECKS/chk_002_python_host_cpu.py
montty/montty_deploy/CHECKS/chk_003_cla_python_host_cpu_etc.py
montty/montty_deploy/CHECKS/chk_004_clf_bash_ss.py
montty/montty_deploy/CHECKS/chk_007_clf_debian_ubuntu_unattended_upgrades.py
montty/montty_deploy/CHECKS/chk_008_clf_rhel_dnf_automatic.py
montty-1.0.3.dist-info/METADATA
montty-1.0.3.dist-info/WHEEL
montty-1.0.3.dist-info/entry_points.txt
montty-1.0.3.dist-info/licenses/LICENSE
montty-1.0.3.dist-info/RECORD
