Metadata-Version: 2.3
Name: montty
Version: 1.0.3
Summary: MonTTY (Monitoring TTY), create system/security checks for Linux hosts, and monitor their results.
Project-URL: Homepage, https://github.com/GwynDavies/montty
Project-URL: Issues, https://github.com/GwynDavies/montty/issues
Author-email: Gwyn Davies <gwynmdavies@cox.net>
Maintainer-email: Gwyn Davies <gwynmdavies@cox.net>
License: MIT License
Keywords: bash,checks,cybersecurity,devops,linux,monitoring,python,secops,system
Requires-Python: >=3.9
Requires-Dist: build
Requires-Dist: keyrings-alt
Requires-Dist: psutil
Provides-Extra: dev
Requires-Dist: autopep8; extra == 'dev'
Requires-Dist: bandit; extra == 'dev'
Requires-Dist: pylint; extra == 'dev'
Requires-Dist: pylint-pytest; extra == 'dev'
Requires-Dist: pytest; extra == 'dev'
Requires-Dist: pytest-cov; extra == 'dev'
Requires-Dist: twine; extra == 'dev'
